{
  "how-to-boil-3-cups-of-water": {
    "0": { "required": ["pot"], "forbidden": ["pan", "bowl"] },
    "1": { "required": [], "forbidden": [] },
    "2": { "required": [], "forbidden": [] }
  },
  "how-to-make-a-sandwich": {
    "0": { "required": ["bread"], "forbidden": ["hot dog bun", "tortilla"] },
    "1": {
      "required": ["knife", "butter"],
      "forbidden": ["spoon", "ketchup"],
      "branchOn": [{ "item": "spoon", "module": "how-to-use-a-knife-safely" }]
    },
    "2": { "required": ["cheese"], "forbidden": ["mustard", "relish"] }
  }
}
